extra_proposal/__init__.py
extra_proposal/mymdc.py
extra_proposal/proposal.py
extra_proposal/utils.py
extra_proposal-0.1.4.dist-info/licenses/LICENSE
extra_proposal-0.1.4.dist-info/WHEEL
extra_proposal-0.1.4.dist-info/METADATA
extra_proposal-0.1.4.dist-info/RECORD
