Metadata-Version: 2.4
Name: EXtra-proposal
Version: 0.1.4
Summary: An interface to a European XFEL proposal
Author-email: James Wrigley <james.wrigley@xfel.eu>, Luca Gelisio <luca.gelisio@xfel.eu>, Thomas Kluyver <thomas.kluyver@xfel.eu>
Requires-Python: >=3.9
License-Expression: BSD-3-Clause
License-File: LICENSE
Requires-Dist: pyyaml
Requires-Dist: requests
Requires-Dist: oauth2_xfel_client
Requires-Dist: matplotlib
Requires-Dist: numpy
Requires-Dist: mkdocs-material ; extra == "docs"
Requires-Dist: mkdocstrings ; extra == "docs"
Requires-Dist: mkdocstrings-python ; extra == "docs"
Requires-Dist: extra-data ; extra == "extra"
Requires-Dist: damnit ; extra == "extra"
Requires-Dist: pandas ; extra == "extra"
Requires-Dist: pytest ; extra == "test"
Requires-Dist: pytest-cov ; extra == "test"
Project-URL: Home, https://github.com/European-XFEL/extra-proposal
Provides-Extra: docs
Provides-Extra: extra
Provides-Extra: test
